widark/__init__.py
widark/application.py
widark/palette.py
widark/widget/__init__.py
widark/widget/components/__init__.py
widark/widget/components/button.py
widark/widget/components/entry.py
widark/widget/components/frame.py
widark/widget/components/label.py
widark/widget/components/listbox.py
widark/widget/components/modal.py
widark/widget/components/spacer.py
widark/widget/event.py
widark/widget/style.py
widark/widget/widget.py
widark-0.3.3.dist-info/LICENSE
widark-0.3.3.dist-info/WHEEL
widark-0.3.3.dist-info/METADATA
widark-0.3.3.dist-info/RECORD
