Metadata-Version: 2.1
Name: widark
Version: 0.3.3
Summary: Widgets for console user interfaces
Author: Knowark
Requires-Python: >=3.6,<4.0
Classifier: Programming Language :: Python :: 3
Classifier: Programming Language :: Python :: 3.6
Classifier: Programming Language :: Python :: 3.7
Classifier: Programming Language :: Python :: 3.8
